openf1_mcp/__init__.py
openf1_mcp/client.py
openf1_mcp/error_handler.py
openf1_mcp/query_builder.py
openf1_mcp/server.py
openf1_mcp_server-0.1.0.dist-info/licenses/LICENSE
openf1_mcp_server-0.1.0.dist-info/METADATA
openf1_mcp_server-0.1.0.dist-info/WHEEL
openf1_mcp_server-0.1.0.dist-info/entry_points.txt
openf1_mcp_server-0.1.0.dist-info/top_level.txt
openf1_mcp_server-0.1.0.dist-info/RECORD
