Metadata-Version: 2.4
Name: openf1-mcp-server
Version: 0.1.0
Summary: A Model Context Protocol server for querying Formula 1 data through the OpenF1 API
Author: Matt Meiers
License: MIT
Project-URL: Homepage, https://github.com/openf1/openf1-mcp-server
Project-URL: Repository, https://github.com/openf1/openf1-mcp-server
Project-URL: Issues, https://github.com/openf1/openf1-mcp-server/issues
Project-URL: Documentation, https://github.com/openf1/openf1-mcp-server#readme
Keywords: mcp,formula1,f1,openf1,api,model-context-protocol
Classifier: Development Status :: 3 - Alpha
Classifier: Intended Audience :: Developers
Classifier: License :: OSI Approved :: MIT License
Classifier: Programming Language :: Python :: 3
Classifier: Programming Language :: Python :: 3.10
Classifier: Programming Language :: Python :: 3.11
Classifier: Programming Language :: Python :: 3.12
Classifier: Topic :: Software Development :: Libraries :: Python Modules
Requires-Python: >=3.10
License-File: LICENSE
Requires-Dist: mcp>=1.0.0
Requires-Dist: httpx>=0.27.0
Requires-Dist: pydantic>=2.0.0
Provides-Extra: dev
Requires-Dist: pytest>=8.0.0; extra == "dev"
Requires-Dist: pytest-asyncio>=0.23.0; extra == "dev"
Requires-Dist: pytest-mock>=3.12.0; extra == "dev"
Requires-Dist: black>=24.0.0; extra == "dev"
Requires-Dist: ruff>=0.3.0; extra == "dev"
Dynamic: license-file
